hkopenai/hk_finance_mcp_server/__init__.py
hkopenai/hk_finance_mcp_server/__main__.py
hkopenai/hk_finance_mcp_server/app.py
hkopenai/hk_finance_mcp_server/tool_business_reg.py
hkopenai/hk_finance_mcp_server/tool_coin_cart.py
hkopenai/hk_finance_mcp_server/tool_credit_card.py
hkopenai/hk_finance_mcp_server/tool_hkma_tender.py
hkopenai/hk_finance_mcp_server/tool_neg_resident_mortgage.py
hkopenai_hk_finance_mcp_server-0.1.7.dist-info/licenses/LICENSE
hkopenai_hk_finance_mcp_server-0.1.7.dist-info/METADATA
hkopenai_hk_finance_mcp_server-0.1.7.dist-info/WHEEL
hkopenai_hk_finance_mcp_server-0.1.7.dist-info/entry_points.txt
hkopenai_hk_finance_mcp_server-0.1.7.dist-info/top_level.txt
hkopenai_hk_finance_mcp_server-0.1.7.dist-info/RECORD
